{
    "openapi": "3.1.0",
    "info": {
        "title": "MoH Service API",
        "version": "4.6.0",
        "description": "This is the RESTful API for the MoH Service."
    },
    "paths": {
        "/v2/service-info": {
            "get": {
                "operationId": "chord_metadata_service_mohpackets_apis_core_service_info",
                "summary": "Service Info",
                "parameters": [],
                "responses": {
                    "200": {
                        "description": "OK"
                    }
                }
            }
        }
    },
    "components": {
        "schemas": {}
    },
    "servers": []
}
