[{"program_id": "SYNTH_01", "submitter_donor_id": "DONOR_0001", "submitter_specimen_id": null, "submitter_primary_diagnosis_id": null, "submitter_treatment_id": null, "submitter_follow_up_id": null, "test_date": {"day_interval": -9100, "month_interval": -299}, "psa_level": 8, "ca125": 39, "cea": 4, "er_status": "Cannot be determined", "er_percent_positive": null, "pr_status": null, "pr_percent_positive": 92.89, "her2_ihc_status": "Equivocal", "her2_ish_status": "Positive", "hpv_ihc_status": "Negative", "hpv_pcr_status": "Unknown", "hpv_strain": null}, {"program_id": "SYNTH_01", "submitter_donor_id": "DONOR_0002", "submitter_specimen_id": "SPECIMEN_0002", "submitter_primary_diagnosis_id": null, "submitter_treatment_id": null, "submitter_follow_up_id": null, "test_date": {"day_interval": 26185, "month_interval": 860}, "psa_level": 0, "ca125": 29, "cea": 3, "er_status": "Unknown", "er_percent_positive": null, "pr_status": "Positive", "pr_percent_positive": 45.69, "her2_ihc_status": null, "her2_ish_status": null, "hpv_ihc_status": null, "hpv_pcr_status": "Unknown", "hpv_strain": null}, {"program_id": "SYNTH_01", "submitter_donor_id": "DONOR_0003", "submitter_specimen_id": null, "submitter_primary_diagnosis_id": "DIAG_0003", "submitter_treatment_id": null, "submitter_follow_up_id": null, "test_date": {"day_interval": -17094, "month_interval": -562}, "psa_level": 14, "ca125": 16, "cea": 6, "er_status": null, "er_percent_positive": 41.64, "pr_status": null, "pr_percent_positive": 63.28, "her2_ihc_status": "Not applicable", "her2_ish_status": "Unknown", "hpv_ihc_status": "Not applicable", "hpv_pcr_status": "Not applicable", "hpv_strain": null}, {"program_id": "SYNTH_01", "submitter_donor_id": "DONOR_0004", "submitter_specimen_id": null, "submitter_primary_diagnosis_id": null, "submitter_treatment_id": "TREATMENT_0007", "submitter_follow_up_id": null, "test_date": {"day_interval": 19600, "month_interval": 643}, "psa_level": 17, "ca125": 41, "cea": 4, "er_status": "Cannot be determined", "er_percent_positive": null, "pr_status": null, "pr_percent_positive": 45.09, "her2_ihc_status": null, "her2_ish_status": null, "hpv_ihc_status": "Not applicable", "hpv_pcr_status": null, "hpv_strain": null}, {"program_id": "SYNTH_01", "submitter_donor_id": "DONOR_0005", "submitter_specimen_id": null, "submitter_primary_diagnosis_id": null, "submitter_treatment_id": null, "submitter_follow_up_id": "FOLLOW_UP_0005", "test_date": {"day_interval": -10619, "month_interval": -349}, "psa_level": 7, "ca125": 35, "cea": 2, "er_status": "Unknown", "er_percent_positive": null, "pr_status": "Negative", "pr_percent_positive": null, "her2_ihc_status": "Positive", "her2_ish_status": null, "hpv_ihc_status": "Unknown", "hpv_pcr_status": "Positive", "hpv_strain": null}, {"program_id": "SYNTH_01", "submitter_donor_id": "DONOR_0006", "submitter_specimen_id": null, "submitter_primary_diagnosis_id": null, "submitter_treatment_id": null, "submitter_follow_up_id": null, "test_date": {"day_interval": 30848, "month_interval": 1013}, "psa_level": 19, "ca125": 0, "cea": 10, "er_status": "Unknown", "er_percent_positive": null, "pr_status": null, "pr_percent_positive": 79.51, "her2_ihc_status": "Negative", "her2_ish_status": "Equivocal", "hpv_ihc_status": null, "hpv_pcr_status": "Positive", "hpv_strain": ["HPV31", "HPV73"]}, {"program_id": "SYNTH_01", "submitter_donor_id": "DONOR_0007", "submitter_specimen_id": "SPECIMEN_0007", "submitter_primary_diagnosis_id": null, "submitter_treatment_id": null, "submitter_follow_up_id": null, "test_date": {"day_interval": 17994, "month_interval": 591}, "psa_level": 8, "ca125": 36, "cea": 2, "er_status": "Unknown", "er_percent_positive": null, "pr_status": "Cannot be determined", "pr_percent_positive": null, "her2_ihc_status": "Not applicable", "her2_ish_status": "Unknown", "hpv_ihc_status": "Negative", "hpv_pcr_status": null, "hpv_strain": null}, {"program_id": "SYNTH_01", "submitter_donor_id": "DONOR_0008", "submitter_specimen_id": null, "submitter_primary_diagnosis_id": "DIAG_0008", "submitter_treatment_id": null, "submitter_follow_up_id": null, "test_date": {"day_interval": 914, "month_interval": 30}, "psa_level": 5, "ca125": 4, "cea": 6, "er_status": null, "er_percent_positive": 14.94, "pr_status": null, "pr_percent_positive": 68.76, "her2_ihc_status": "Unknown", "her2_ish_status": "Unknown", "hpv_ihc_status": "Negative", "hpv_pcr_status": null, "hpv_strain": null}, {"program_id": "SYNTH_01", "submitter_donor_id": "DONOR_0009", "submitter_specimen_id": null, "submitter_primary_diagnosis_id": null, "submitter_treatment_id": "TREATMENT_0017", "submitter_follow_up_id": null, "test_date": {"day_interval": 25488, "month_interval": 837}, "psa_level": 16, "ca125": 36, "cea": 7, "er_status": null, "er_percent_positive": 97.52, "pr_status": "Positive", "pr_percent_positive": 48.32, "her2_ihc_status": "Positive", "her2_ish_status": "Cannot be determined", "hpv_ihc_status": "Positive", "hpv_pcr_status": "Positive", "hpv_strain": null}, {"program_id": "SYNTH_01", "submitter_donor_id": "DONOR_0010", "submitter_specimen_id": null, "submitter_primary_diagnosis_id": null, "submitter_treatment_id": null, "submitter_follow_up_id": "FOLLOW_UP_0010", "test_date": {"day_interval": -14824, "month_interval": -488}, "psa_level": 9, "ca125": 50, "cea": 4, "er_status": "Unknown", "er_percent_positive": null, "pr_status": "Cannot be determined", "pr_percent_positive": null, "her2_ihc_status": "Not applicable", "her2_ish_status": "Positive", "hpv_ihc_status": null, "hpv_pcr_status": null, "hpv_strain": null}, {"program_id": "SYNTH_02", "submitter_donor_id": "DONOR_0021", "submitter_specimen_id": null, "submitter_primary_diagnosis_id": null, "submitter_treatment_id": null, "submitter_follow_up_id": null, "test_date": null, "psa_level": 12, "ca125": 11, "cea": 8, "er_status": "Negative", "er_percent_positive": null, "pr_status": "Negative", "pr_percent_positive": null, "her2_ihc_status": "Positive", "her2_ish_status": "Negative", "hpv_ihc_status": "Positive", "hpv_pcr_status": null, "hpv_strain": null}, {"program_id": "SYNTH_02", "submitter_donor_id": "DONOR_0022", "submitter_specimen_id": "SPECIMEN_0022", "submitter_primary_diagnosis_id": null, "submitter_treatment_id": null, "submitter_follow_up_id": null, "test_date": null, "psa_level": 11, "ca125": 7, "cea": 9, "er_status": null, "er_percent_positive": 47.37, "pr_status": "Cannot be determined", "pr_percent_positive": null, "her2_ihc_status": "Negative", "her2_ish_status": null, "hpv_ihc_status": null, "hpv_pcr_status": "Unknown", "hpv_strain": null}, {"program_id": "SYNTH_02", "submitter_donor_id": "DONOR_0023", "submitter_specimen_id": null, "submitter_primary_diagnosis_id": "DIAG_0023", "submitter_treatment_id": null, "submitter_follow_up_id": null, "test_date": {"day_interval": 28744, "month_interval": 944}, "psa_level": 20, "ca125": 22, "cea": 9, "er_status": null, "er_percent_positive": 7.39, "pr_status": "Negative", "pr_percent_positive": null, "her2_ihc_status": "Unknown", "her2_ish_status": "Equivocal", "hpv_ihc_status": "Positive", "hpv_pcr_status": "Negative", "hpv_strain": null}, {"program_id": "SYNTH_02", "submitter_donor_id": "DONOR_0024", "submitter_specimen_id": null, "submitter_primary_diagnosis_id": null, "submitter_treatment_id": "TREATMENT_0047", "submitter_follow_up_id": null, "test_date": {"day_interval": 32825, "month_interval": 1078}, "psa_level": 7, "ca125": 35, "cea": 6, "er_status": null, "er_percent_positive": 80.73, "pr_status": "Not applicable", "pr_percent_positive": null, "her2_ihc_status": "Negative", "her2_ish_status": null, "hpv_ihc_status": null, "hpv_pcr_status": "Unknown", "hpv_strain": null}, {"program_id": "SYNTH_02", "submitter_donor_id": "DONOR_0025", "submitter_specimen_id": null, "submitter_primary_diagnosis_id": null, "submitter_treatment_id": null, "submitter_follow_up_id": "FOLLOW_UP_0015", "test_date": {"day_interval": 21424, "month_interval": 703}, "psa_level": 15, "ca125": 43, "cea": 8, "er_status": "Negative", "er_percent_positive": null, "pr_status": "Cannot be determined", "pr_percent_positive": null, "her2_ihc_status": "Not applicable", "her2_ish_status": "Negative", "hpv_ihc_status": "Unknown", "hpv_pcr_status": "Cannot be determined", "hpv_strain": ["HPV73", "HPV16"]}, {"program_id": "SYNTH_02", "submitter_donor_id": "DONOR_0026", "submitter_specimen_id": null, "submitter_primary_diagnosis_id": null, "submitter_treatment_id": null, "submitter_follow_up_id": null, "test_date": {"day_interval": 7430, "month_interval": 244}, "psa_level": 16, "ca125": 44, "cea": 7, "er_status": null, "er_percent_positive": 6.32, "pr_status": "Positive", "pr_percent_positive": 92.82, "her2_ihc_status": "Negative", "her2_ish_status": null, "hpv_ihc_status": null, "hpv_pcr_status": "Cannot be determined", "hpv_strain": null}, {"program_id": "SYNTH_02", "submitter_donor_id": "DONOR_0027", "submitter_specimen_id": "SPECIMEN_0027", "submitter_primary_diagnosis_id": null, "submitter_treatment_id": null, "submitter_follow_up_id": null, "test_date": {"day_interval": -13214, "month_interval": -435}, "psa_level": 15, "ca125": 9, "cea": 1, "er_status": null, "er_percent_positive": 74.04, "pr_status": "Positive", "pr_percent_positive": 1.64, "her2_ihc_status": "Equivocal", "her2_ish_status": null, "hpv_ihc_status": null, "hpv_pcr_status": "Positive", "hpv_strain": null}, {"program_id": "SYNTH_02", "submitter_donor_id": "DONOR_0028", "submitter_specimen_id": null, "submitter_primary_diagnosis_id": "DIAG_0028", "submitter_treatment_id": null, "submitter_follow_up_id": null, "test_date": null, "psa_level": 3, "ca125": 38, "cea": 8, "er_status": "Unknown", "er_percent_positive": null, "pr_status": null, "pr_percent_positive": 33.87, "her2_ihc_status": "Positive", "her2_ish_status": null, "hpv_ihc_status": null, "hpv_pcr_status": "Negative", "hpv_strain": null}, {"program_id": "SYNTH_02", "submitter_donor_id": "DONOR_0029", "submitter_specimen_id": null, "submitter_primary_diagnosis_id": null, "submitter_treatment_id": "TREATMENT_0057", "submitter_follow_up_id": null, "test_date": {"day_interval": 14656, "month_interval": 481}, "psa_level": 5, "ca125": 1, "cea": 9, "er_status": "Cannot be determined", "er_percent_positive": null, "pr_status": "Positive", "pr_percent_positive": 12.1, "her2_ihc_status": null, "her2_ish_status": null, "hpv_ihc_status": null, "hpv_pcr_status": null, "hpv_strain": null}, {"program_id": "SYNTH_02", "submitter_donor_id": "DONOR_0030", "submitter_specimen_id": null, "submitter_primary_diagnosis_id": null, "submitter_treatment_id": null, "submitter_follow_up_id": "FOLLOW_UP_0020", "test_date": {"day_interval": 25199, "month_interval": 827}, "psa_level": 10, "ca125": 25, "cea": 1, "er_status": null, "er_percent_positive": 60.24, "pr_status": "Unknown", "pr_percent_positive": null, "her2_ihc_status": null, "her2_ish_status": null, "hpv_ihc_status": null, "hpv_pcr_status": "Positive", "hpv_strain": null}, {"program_id": "SYNTH_03", "submitter_donor_id": "DONOR_0041", "submitter_specimen_id": null, "submitter_primary_diagnosis_id": null, "submitter_treatment_id": null, "submitter_follow_up_id": null, "test_date": {"day_interval": -6393, "month_interval": -211}, "psa_level": 13, "ca125": 34, "cea": 8, "er_status": null, "er_percent_positive": 62.28, "pr_status": "Negative", "pr_percent_positive": null, "her2_ihc_status": "Cannot be determined", "her2_ish_status": "Not applicable", "hpv_ihc_status": null, "hpv_pcr_status": "Not applicable", "hpv_strain": null}, {"program_id": "SYNTH_03", "submitter_donor_id": "DONOR_0042", "submitter_specimen_id": "SPECIMEN_0042", "submitter_primary_diagnosis_id": null, "submitter_treatment_id": null, "submitter_follow_up_id": null, "test_date": {"day_interval": 29524, "month_interval": 970}, "psa_level": 15, "ca125": 45, "cea": 10, "er_status": "Positive", "er_percent_positive": 4.53, "pr_status": null, "pr_percent_positive": 73.12, "her2_ihc_status": "Unknown", "her2_ish_status": null, "hpv_ihc_status": "Negative", "hpv_pcr_status": "Negative", "hpv_strain": null}, {"program_id": "SYNTH_03", "submitter_donor_id": "DONOR_0043", "submitter_specimen_id": null, "submitter_primary_diagnosis_id": "DIAG_0043", "submitter_treatment_id": null, "submitter_follow_up_id": null, "test_date": {"day_interval": 25452, "month_interval": 836}, "psa_level": 6, "ca125": 22, "cea": 4, "er_status": null, "er_percent_positive": 18.48, "pr_status": "Negative", "pr_percent_positive": null, "her2_ihc_status": null, "her2_ish_status": "Not applicable", "hpv_ihc_status": null, "hpv_pcr_status": null, "hpv_strain": null}, {"program_id": "SYNTH_03", "submitter_donor_id": "DONOR_0044", "submitter_specimen_id": null, "submitter_primary_diagnosis_id": null, "submitter_treatment_id": "TREATMENT_0087", "submitter_follow_up_id": null, "test_date": null, "psa_level": 3, "ca125": 10, "cea": 9, "er_status": "Unknown", "er_percent_positive": null, "pr_status": "Cannot be determined", "pr_percent_positive": null, "her2_ihc_status": null, "her2_ish_status": null, "hpv_ihc_status": null, "hpv_pcr_status": "Negative", "hpv_strain": null}, {"program_id": "SYNTH_03", "submitter_donor_id": "DONOR_0045", "submitter_specimen_id": null, "submitter_primary_diagnosis_id": null, "submitter_treatment_id": null, "submitter_follow_up_id": "FOLLOW_UP_0025", "test_date": {"day_interval": -5415, "month_interval": -178}, "psa_level": 3, "ca125": 38, "cea": 5, "er_status": "Not applicable", "er_percent_positive": null, "pr_status": null, "pr_percent_positive": 41.01, "her2_ihc_status": null, "her2_ish_status": "Not applicable", "hpv_ihc_status": "Unknown", "hpv_pcr_status": "Unknown", "hpv_strain": ["HPV58", "HPV39"]}, {"program_id": "SYNTH_03", "submitter_donor_id": "DONOR_0046", "submitter_specimen_id": null, "submitter_primary_diagnosis_id": null, "submitter_treatment_id": null, "submitter_follow_up_id": null, "test_date": {"day_interval": 13013, "month_interval": 427}, "psa_level": 9, "ca125": 50, "cea": 1, "er_status": "Negative", "er_percent_positive": null, "pr_status": "Cannot be determined", "pr_percent_positive": null, "her2_ihc_status": "Negative", "her2_ish_status": "Not applicable", "hpv_ihc_status": "Unknown", "hpv_pcr_status": null, "hpv_strain": null}, {"program_id": "SYNTH_03", "submitter_donor_id": "DONOR_0047", "submitter_specimen_id": "SPECIMEN_0047", "submitter_primary_diagnosis_id": null, "submitter_treatment_id": null, "submitter_follow_up_id": null, "test_date": {"day_interval": 29745, "month_interval": 977}, "psa_level": 15, "ca125": 40, "cea": 4, "er_status": null, "er_percent_positive": 98.03, "pr_status": "Positive", "pr_percent_positive": 34.04, "her2_ihc_status": "Cannot be determined", "her2_ish_status": null, "hpv_ihc_status": "Negative", "hpv_pcr_status": null, "hpv_strain": null}, {"program_id": "SYNTH_03", "submitter_donor_id": "DONOR_0048", "submitter_specimen_id": null, "submitter_primary_diagnosis_id": "DIAG_0048", "submitter_treatment_id": null, "submitter_follow_up_id": null, "test_date": {"day_interval": 32249, "month_interval": 1059}, "psa_level": 20, "ca125": 16, "cea": 1, "er_status": null, "er_percent_positive": 93.62, "pr_status": "Negative", "pr_percent_positive": null, "her2_ihc_status": "Unknown", "her2_ish_status": null, "hpv_ihc_status": null, "hpv_pcr_status": "Not applicable", "hpv_strain": ["HPV39", "HPV73"]}, {"program_id": "SYNTH_03", "submitter_donor_id": "DONOR_0049", "submitter_specimen_id": null, "submitter_primary_diagnosis_id": null, "submitter_treatment_id": "TREATMENT_0097", "submitter_follow_up_id": null, "test_date": {"day_interval": 9817, "month_interval": 322}, "psa_level": 6, "ca125": 41, "cea": 4, "er_status": "Cannot be determined", "er_percent_positive": null, "pr_status": "Positive", "pr_percent_positive": 2.83, "her2_ihc_status": "Negative", "her2_ish_status": "Cannot be determined", "hpv_ihc_status": "Positive", "hpv_pcr_status": "Not applicable", "hpv_strain": null}, {"program_id": "SYNTH_03", "submitter_donor_id": "DONOR_0050", "submitter_specimen_id": null, "submitter_primary_diagnosis_id": null, "submitter_treatment_id": null, "submitter_follow_up_id": "FOLLOW_UP_0030", "test_date": {"day_interval": 13398, "month_interval": 440}, "psa_level": 5, "ca125": 12, "cea": 0, "er_status": "Positive", "er_percent_positive": 11.31, "pr_status": "Unknown", "pr_percent_positive": null, "her2_ihc_status": null, "her2_ish_status": "Not applicable", "hpv_ihc_status": "Cannot be determined", "hpv_pcr_status": "Negative", "hpv_strain": null}, {"program_id": "SYNTH_04", "submitter_donor_id": "DONOR_0061", "submitter_specimen_id": null, "submitter_primary_diagnosis_id": null, "submitter_treatment_id": null, "submitter_follow_up_id": null, "test_date": {"day_interval": 10228, "month_interval": 336}, "psa_level": 0, "ca125": 0, "cea": 3, "er_status": "Cannot be determined", "er_percent_positive": null, "pr_status": "Negative", "pr_percent_positive": null, "her2_ihc_status": null, "her2_ish_status": null, "hpv_ihc_status": null, "hpv_pcr_status": null, "hpv_strain": null}, {"program_id": "SYNTH_04", "submitter_donor_id": "DONOR_0062", "submitter_specimen_id": "SPECIMEN_0062", "submitter_primary_diagnosis_id": null, "submitter_treatment_id": null, "submitter_follow_up_id": null, "test_date": {"day_interval": 9684, "month_interval": 318}, "psa_level": 19, "ca125": 1, "cea": 10, "er_status": "Positive", "er_percent_positive": 0.62, "pr_status": null, "pr_percent_positive": 7.81, "her2_ihc_status": "Not applicable", "her2_ish_status": "Positive", "hpv_ihc_status": "Positive", "hpv_pcr_status": "Not applicable", "hpv_strain": null}, {"program_id": "SYNTH_04", "submitter_donor_id": "DONOR_0063", "submitter_specimen_id": null, "submitter_primary_diagnosis_id": "DIAG_0063", "submitter_treatment_id": null, "submitter_follow_up_id": null, "test_date": null, "psa_level": 1, "ca125": 41, "cea": 2, "er_status": "Negative", "er_percent_positive": null, "pr_status": "Not applicable", "pr_percent_positive": null, "her2_ihc_status": "Not applicable", "her2_ish_status": null, "hpv_ihc_status": "Negative", "hpv_pcr_status": "Unknown", "hpv_strain": null}, {"program_id": "SYNTH_04", "submitter_donor_id": "DONOR_0064", "submitter_specimen_id": null, "submitter_primary_diagnosis_id": null, "submitter_treatment_id": "TREATMENT_0127", "submitter_follow_up_id": null, "test_date": {"day_interval": 25853, "month_interval": 849}, "psa_level": 2, "ca125": 7, "cea": 8, "er_status": "Cannot be determined", "er_percent_positive": null, "pr_status": null, "pr_percent_positive": 91.61, "her2_ihc_status": "Negative", "her2_ish_status": null, "hpv_ihc_status": "Negative", "hpv_pcr_status": null, "hpv_strain": null}, {"program_id": "SYNTH_04", "submitter_donor_id": "DONOR_0065", "submitter_specimen_id": null, "submitter_primary_diagnosis_id": null, "submitter_treatment_id": null, "submitter_follow_up_id": "FOLLOW_UP_0035", "test_date": {"day_interval": 7253, "month_interval": 238}, "psa_level": 7, "ca125": 49, "cea": 6, "er_status": null, "er_percent_positive": 18.63, "pr_status": null, "pr_percent_positive": 69.94, "her2_ihc_status": "Cannot be determined", "her2_ish_status": "Cannot be determined", "hpv_ihc_status": "Unknown", "hpv_pcr_status": "Not applicable", "hpv_strain": null}, {"program_id": "SYNTH_04", "submitter_donor_id": "DONOR_0066", "submitter_specimen_id": null, "submitter_primary_diagnosis_id": null, "submitter_treatment_id": null, "submitter_follow_up_id": null, "test_date": null, "psa_level": 20, "ca125": 32, "cea": 9, "er_status": "Not applicable", "er_percent_positive": null, "pr_status": "Cannot be determined", "pr_percent_positive": null, "her2_ihc_status": "Cannot be determined", "her2_ish_status": "Equivocal", "hpv_ihc_status": "Negative", "hpv_pcr_status": null, "hpv_strain": null}, {"program_id": "SYNTH_04", "submitter_donor_id": "DONOR_0067", "submitter_specimen_id": "SPECIMEN_0067", "submitter_primary_diagnosis_id": null, "submitter_treatment_id": null, "submitter_follow_up_id": null, "test_date": {"day_interval": 4871, "month_interval": 160}, "psa_level": 2, "ca125": 36, "cea": 3, "er_status": "Positive", "er_percent_positive": 59.63, "pr_status": "Not applicable", "pr_percent_positive": null, "her2_ihc_status": "Equivocal", "her2_ish_status": "Cannot be determined", "hpv_ihc_status": "Negative", "hpv_pcr_status": "Positive", "hpv_strain": null}, {"program_id": "SYNTH_04", "submitter_donor_id": "DONOR_0068", "submitter_specimen_id": null, "submitter_primary_diagnosis_id": "DIAG_0068", "submitter_treatment_id": null, "submitter_follow_up_id": null, "test_date": {"day_interval": 20588, "month_interval": 676}, "psa_level": 12, "ca125": 15, "cea": 10, "er_status": "Negative", "er_percent_positive": null, "pr_status": "Positive", "pr_percent_positive": 78.2, "her2_ihc_status": "Positive", "her2_ish_status": "Unknown", "hpv_ihc_status": null, "hpv_pcr_status": "Negative", "hpv_strain": ["HPV66", "HPV51"]}, {"program_id": "SYNTH_04", "submitter_donor_id": "DONOR_0069", "submitter_specimen_id": null, "submitter_primary_diagnosis_id": null, "submitter_treatment_id": "TREATMENT_0137", "submitter_follow_up_id": null, "test_date": {"day_interval": 14918, "month_interval": 490}, "psa_level": 10, "ca125": 49, "cea": 8, "er_status": null, "er_percent_positive": 41.61, "pr_status": "Cannot be determined", "pr_percent_positive": null, "her2_ihc_status": null, "her2_ish_status": null, "hpv_ihc_status": "Cannot be determined", "hpv_pcr_status": "Positive", "hpv_strain": null}, {"program_id": "SYNTH_04", "submitter_donor_id": "DONOR_0070", "submitter_specimen_id": null, "submitter_primary_diagnosis_id": null, "submitter_treatment_id": null, "submitter_follow_up_id": "FOLLOW_UP_0040", "test_date": null, "psa_level": 10, "ca125": 24, "cea": 2, "er_status": "Negative", "er_percent_positive": null, "pr_status": null, "pr_percent_positive": 16.45, "her2_ihc_status": null, "her2_ish_status": null, "hpv_ihc_status": "Positive", "hpv_pcr_status": null, "hpv_strain": null}, {"program_id": "SYNTH_01", "submitter_donor_id": "DONOR_NULL_0001", "submitter_specimen_id": null, "submitter_primary_diagnosis_id": null, "submitter_treatment_id": null, "submitter_follow_up_id": null, "test_date": null, "psa_level": null, "ca125": null, "cea": null, "er_status": null, "er_percent_positive": null, "pr_status": null, "pr_percent_positive": null, "her2_ihc_status": null, "her2_ish_status": null, "hpv_ihc_status": null, "hpv_pcr_status": null, "hpv_strain": null}, {"program_id": "SYNTH_01", "submitter_donor_id": "DONOR_NULL_0002", "submitter_specimen_id": "SPECIMEN_NULL_0002", "submitter_primary_diagnosis_id": null, "submitter_treatment_id": null, "submitter_follow_up_id": null, "test_date": null, "psa_level": null, "ca125": null, "cea": null, "er_status": null, "er_percent_positive": null, "pr_status": null, "pr_percent_positive": null, "her2_ihc_status": null, "her2_ish_status": null, "hpv_ihc_status": null, "hpv_pcr_status": null, "hpv_strain": null}, {"program_id": "SYNTH_01", "submitter_donor_id": "DONOR_ALL_0001", "submitter_specimen_id": null, "submitter_primary_diagnosis_id": "DIAG_ALL_0001", "submitter_treatment_id": null, "submitter_follow_up_id": null, "test_date": {"day_interval": 4011, "month_interval": 131}, "psa_level": 2, "ca125": 27, "cea": 3, "er_status": "Unknown", "er_percent_positive": null, "pr_status": "Not applicable", "pr_percent_positive": null, "her2_ihc_status": "Unknown", "her2_ish_status": "Equivocal", "hpv_ihc_status": "Cannot be determined", "hpv_pcr_status": "Unknown", "hpv_strain": ["HPV31", "HPV45", "HPV16", "HPV56"]}, {"program_id": "SYNTH_01", "submitter_donor_id": "DONOR_ALL_0002", "submitter_specimen_id": null, "submitter_primary_diagnosis_id": null, "submitter_treatment_id": "TREATMENT_ALL_0003", "submitter_follow_up_id": null, "test_date": {"day_interval": 19876, "month_interval": 653}, "psa_level": 2, "ca125": 10, "cea": 9, "er_status": "Cannot be determined", "er_percent_positive": null, "pr_status": "Unknown", "pr_percent_positive": null, "her2_ihc_status": "Negative", "her2_ish_status": "Cannot be determined", "hpv_ihc_status": "Negative", "hpv_pcr_status": "Negative", "hpv_strain": ["HPV45", "HPV51", "HPV68", "HPV35"]}]