[
    {
        "date_of_diagnosis": {
            "month_interval": 3,
            "day_interval": 90
        },
        "cancer_type_code": "C02.1",
        "basis_of_diagnosis": "Cytology",
        "lymph_nodes_examined_status": "Not applicable",
        "lymph_nodes_examined_method": "Imaging",
        "number_lymph_nodes_positive": 9,
        "clinical_tumour_staging_system": "Ann Arbor staging system",
        "clinical_t_category": "T4d",
        "clinical_m_category": "M1a(1)",
        "clinical_stage_group": "Stage IIIAE",
        "laterality": "Midline",
        "submitter_primary_diagnosis_id": "PRIMARY_DIAGNOSIS_1",
        "submitter_donor_id": "DONOR_1",
        "program_id": "SYNTHETIC-1"
    },
    {
        "date_of_diagnosis": {
            "month_interval": 30,
            "day_interval": 900
        },
        "cancer_type_code": "C06.9",
        "lymph_nodes_examined_status": "Yes",
        "number_lymph_nodes_positive": 3,
        "clinical_tumour_staging_system": "Lugano staging system",
        "clinical_t_category": "T2d",
        "clinical_n_category": "N0(i-)",
        "clinical_stage_group": "Stage IIA2",
        "laterality": "Midline",
        "submitter_primary_diagnosis_id": "PRIMARY_DIAGNOSIS_2",
        "submitter_donor_id": "DONOR_1",
        "program_id": "SYNTHETIC-1"
    },
    {
        "date_of_diagnosis": {
            "month_interval": 1,
            "day_interval": 30
        },
        "cancer_type_code": "C34.9",
        "basis_of_diagnosis": "Unknown",
        "lymph_nodes_examined_status": "No",
        "lymph_nodes_examined_method": "Physical palpation of patient",
        "number_lymph_nodes_positive": 8,
        "clinical_tumour_staging_system": "Ann Arbor staging system",
        "clinical_t_category": "T3e",
        "clinical_n_category": "N0(mol+)",
        "clinical_stage_group": "Stage IVAS",
        "laterality": "Unilateral, side not specified",
        "submitter_primary_diagnosis_id": "PRIMARY_DIAGNOSIS_3",
        "submitter_donor_id": "DONOR_1",
        "program_id": "SYNTHETIC-1"
    },
    {
        "date_of_diagnosis": {
            "month_interval": 64,
            "day_interval": 1920
        },
        "cancer_type_code": "C18.9",
        "basis_of_diagnosis": "Clinical investigation",
        "lymph_nodes_examined_method": "Lymph node dissection/pathological exam",
        "clinical_tumour_staging_system": "Lugano staging system",
        "clinical_t_category": "T2(s)",
        "clinical_n_category": "NX",
        "clinical_m_category": "M1a(0)",
        "clinical_stage_group": "Stage L1",
        "laterality": "Unilateral, side not specified",
        "submitter_primary_diagnosis_id": "PRIMARY_DIAGNOSIS_4",
        "submitter_donor_id": "DONOR_2",
        "program_id": "SYNTHETIC-1"
    },
    {
        "date_of_diagnosis": {
            "month_interval": 64,
            "day_interval": 1920
        },
        "cancer_type_code": "C67.6",
        "basis_of_diagnosis": "Clinical investigation",
        "lymph_nodes_examined_status": "Not applicable",
        "lymph_nodes_examined_method": "Imaging",
        "number_lymph_nodes_positive": 14,
        "clinical_tumour_staging_system": "AJCC 6th edition",
        "clinical_t_category": "Tis(LCIS)",
        "clinical_n_category": "N3b",
        "clinical_stage_group": "Stage I",
        "laterality": "Not a paired site",
        "submitter_primary_diagnosis_id": "PRIMARY_DIAGNOSIS_5",
        "submitter_donor_id": "DONOR_2",
        "program_id": "SYNTHETIC-1"
    },
    {
        "date_of_diagnosis": {
            "month_interval": 12,
            "day_interval": 360
        },
        "cancer_type_code": "C43.9",
        "basis_of_diagnosis": "Cytology",
        "lymph_nodes_examined_status": "Not applicable",
        "number_lymph_nodes_positive": 12,
        "clinical_tumour_staging_system": "AJCC 7th edition",
        "clinical_t_category": "T3d",
        "clinical_n_category": "N0a (biopsy)",
        "clinical_m_category": "M0",
        "laterality": "Unknown",
        "submitter_primary_diagnosis_id": "PRIMARY_DIAGNOSIS_6",
        "submitter_donor_id": "DONOR_2",
        "program_id": "SYNTHETIC-1"
    },
    {
        "date_of_diagnosis": {
            "month_interval": 81,
            "day_interval": 2430
        },
        "basis_of_diagnosis": "Cytology",
        "lymph_nodes_examined_status": "Not applicable",
        "lymph_nodes_examined_method": "Lymph node dissection/pathological exam",
        "number_lymph_nodes_positive": 6,
        "clinical_t_category": "T4b(s)",
        "clinical_n_category": "N1c",
        "clinical_m_category": "M1c(0)",
        "clinical_stage_group": "Stage IES",
        "laterality": "Unknown",
        "submitter_primary_diagnosis_id": "PRIMARY_DIAGNOSIS_7",
        "submitter_donor_id": "DONOR_3",
        "program_id": "SYNTHETIC-1"
    },
    {
        "date_of_diagnosis": {
            "month_interval": 21,
            "day_interval": 630
        },
        "cancer_type_code": "C67.6",
        "basis_of_diagnosis": "Cytology",
        "lymph_nodes_examined_method": "Lymph node dissection/pathological exam",
        "number_lymph_nodes_positive": 12,
        "clinical_tumour_staging_system": "Revised International staging system (RISS)",
        "clinical_t_category": "TX",
        "clinical_n_category": "N2",
        "clinical_m_category": "M0",
        "clinical_stage_group": "Stage IIBS",
        "laterality": "Left",
        "submitter_primary_diagnosis_id": "PRIMARY_DIAGNOSIS_8",
        "submitter_donor_id": "DONOR_3",
        "program_id": "SYNTHETIC-1"
    },
    {
        "date_of_diagnosis": {
            "month_interval": 30,
            "day_interval": 900
        },
        "cancer_type_code": "C43.9",
        "basis_of_diagnosis": "Cytology",
        "lymph_nodes_examined_status": "Yes",
        "lymph_nodes_examined_method": "Lymph node dissection/pathological exam",
        "number_lymph_nodes_positive": 4,
        "clinical_t_category": "T4a(s)",
        "clinical_n_category": "N2b",
        "clinical_m_category": "M0",
        "clinical_stage_group": "Stage IIIA",
        "submitter_primary_diagnosis_id": "PRIMARY_DIAGNOSIS_9",
        "submitter_donor_id": "DONOR_4",
        "program_id": "SYNTHETIC-1"
    },
    {
        "date_of_diagnosis": {
            "month_interval": 43,
            "day_interval": 1290
        },
        "cancer_type_code": "C02.1",
        "basis_of_diagnosis": "Histology of a metastasis",
        "lymph_nodes_examined_status": "Not applicable",
        "number_lymph_nodes_positive": 14,
        "clinical_tumour_staging_system": "AJCC 6th edition",
        "clinical_t_category": "T2a1",
        "clinical_n_category": "N3b",
        "clinical_m_category": "M1c(0)",
        "clinical_stage_group": "Stage IBE",
        "laterality": "Left",
        "submitter_primary_diagnosis_id": "PRIMARY_DIAGNOSIS_10",
        "submitter_donor_id": "DONOR_4",
        "program_id": "SYNTHETIC-1"
    },
    {
        "date_of_diagnosis": {
            "month_interval": 70,
            "day_interval": 2100
        },
        "cancer_type_code": "C43.9",
        "basis_of_diagnosis": "Clinical investigation",
        "lymph_nodes_examined_status": "Yes",
        "lymph_nodes_examined_method": "Imaging",
        "number_lymph_nodes_positive": 9,
        "clinical_tumour_staging_system": "AJCC 7th edition",
        "clinical_t_category": "Tis(LCIS)",
        "clinical_m_category": "M1d(0)",
        "clinical_stage_group": "Stage IS",
        "laterality": "Left",
        "submitter_primary_diagnosis_id": "PRIMARY_DIAGNOSIS_11",
        "submitter_donor_id": "DONOR_5",
        "program_id": "SYNTHETIC-1"
    },
    {
        "date_of_diagnosis": {
            "month_interval": 20,
            "day_interval": 600
        },
        "cancer_type_code": "C04.0",
        "basis_of_diagnosis": "Clinical",
        "lymph_nodes_examined_status": "Cannot be determined",
        "lymph_nodes_examined_method": "Imaging",
        "number_lymph_nodes_positive": 8,
        "clinical_tumour_staging_system": "SEER staging system",
        "clinical_t_category": "T1a1",
        "clinical_n_category": "N1a(sn)",
        "clinical_m_category": "M1b(0)",
        "laterality": "Not a paired site",
        "submitter_primary_diagnosis_id": "PRIMARY_DIAGNOSIS_12",
        "submitter_donor_id": "DONOR_6",
        "program_id": "SYNTHETIC-1"
    },
    {
        "date_of_diagnosis": {
            "month_interval": 25,
            "day_interval": 750
        },
        "lymph_nodes_examined_status": "Not applicable",
        "lymph_nodes_examined_method": "Lymph node dissection/pathological exam",
        "number_lymph_nodes_positive": 15,
        "clinical_tumour_staging_system": "AJCC 6th edition",
        "clinical_t_category": "TX",
        "clinical_n_category": "N0a",
        "clinical_m_category": "M1d(1)",
        "clinical_stage_group": "Stage II bulky",
        "laterality": "Bilateral",
        "submitter_primary_diagnosis_id": "PRIMARY_DIAGNOSIS_13",
        "submitter_donor_id": "DONOR_7",
        "program_id": "SYNTHETIC-2"
    },
    {
        "date_of_diagnosis": {
            "month_interval": 89,
            "day_interval": 2670
        },
        "cancer_type_code": "C67.6",
        "basis_of_diagnosis": "Death certificate only",
        "lymph_nodes_examined_status": "No lymph nodes found in resected specimen",
        "lymph_nodes_examined_method": "Lymph node dissection/pathological exam",
        "number_lymph_nodes_positive": 3,
        "clinical_tumour_staging_system": "AJCC 7th edition",
        "clinical_t_category": "Tis(LAMN)",
        "clinical_n_category": "N3a",
        "clinical_stage_group": "Stage IBE",
        "laterality": "Right",
        "submitter_primary_diagnosis_id": "PRIMARY_DIAGNOSIS_14",
        "submitter_donor_id": "DONOR_8",
        "program_id": "SYNTHETIC-2"
    },
    {
        "date_of_diagnosis": {
            "month_interval": 31,
            "day_interval": 930
        },
        "cancer_type_code": "C43.9",
        "basis_of_diagnosis": "Cytology",
        "lymph_nodes_examined_status": "No lymph nodes found in resected specimen",
        "lymph_nodes_examined_method": "Physical palpation of patient",
        "number_lymph_nodes_positive": 9,
        "clinical_tumour_staging_system": "St Jude staging system",
        "clinical_t_category": "Tis(Paget's)",
        "clinical_n_category": "N2b",
        "clinical_m_category": "M1c(0)",
        "clinical_stage_group": "Stage IIAS",
        "laterality": "Right",
        "submitter_primary_diagnosis_id": "PRIMARY_DIAGNOSIS_15",
        "submitter_donor_id": "DONOR_9",
        "program_id": "SYNTHETIC-2"
    },
    {
        "date_of_diagnosis": {
            "month_interval": 69,
            "day_interval": 2070
        },
        "cancer_type_code": "C67.6",
        "basis_of_diagnosis": "Specific tumour markers",
        "lymph_nodes_examined_status": "No lymph nodes found in resected specimen",
        "lymph_nodes_examined_method": "Imaging",
        "number_lymph_nodes_positive": 10,
        "clinical_t_category": "TX",
        "clinical_n_category": "N0b (no biopsy)",
        "clinical_m_category": "M1a(1)",
        "laterality": "Right",
        "submitter_primary_diagnosis_id": "PRIMARY_DIAGNOSIS_16",
        "submitter_donor_id": "DONOR_10",
        "program_id": "SYNTHETIC-2"
    }
]